bvill_apdft/__init__.py
bvill_apdft/apdft.py
bvill_apdft/cli.py
bvill_apdft/tests/__init__.py
bvill_apdft/tests/test_apdft.py
bvill_apdft/utils.py
bvill.apdft-0.1.0a1.dist-info/entry_points.txt
bvill.apdft-0.1.0a1.dist-info/LICENSE
bvill.apdft-0.1.0a1.dist-info/WHEEL
bvill.apdft-0.1.0a1.dist-info/METADATA
bvill.apdft-0.1.0a1.dist-info/RECORD
