Metadata-Version: 2.1
Name: bvill.apdft
Version: 0.1.0a1
Summary: Another PDF Tool helps you quickly operate on PDF files with actions such as rotate, merging, and splitting via the command-line. Currently only supports merging.
Home-page: https://github.com/bvillagran/apdft
License: MIT
Keywords: pdf,command-line,utilities
Author: Brandon Villagran
Author-email: bvillagran.dev@gmail.com
Requires-Python: >=3.6,<4.0
Classifier: Environment :: Console
Classifier: Intended Audience :: Developers
Classifier: Intended Audience :: Education
Classifier: Intended Audience :: End Users/Desktop
Classifier: License :: OSI Approved :: MIT License
Classifier: Natural Language :: English
Classifier: Operating System :: OS Independent
Classifier: Programming Language :: Python
Classifier: Programming Language :: Python :: 3
Classifier: Programming Language :: Python :: 3.6
Classifier: Programming Language :: Python :: 3.7
Classifier: Programming Language :: Python :: 3.8
Classifier: Topic :: Multimedia :: Graphics :: Presentation
Classifier: Topic :: Office/Business
Classifier: Topic :: Text Processing :: General
Classifier: Topic :: Utilities
Requires-Dist: PyPDF2 (>=1.26.0,<2.0.0)
Requires-Dist: click (>=7.1.1,<8.0.0)
Project-URL: Repository, https://github.com/bvillagran/apdft
